np_payments/__init__.py
np_payments/base.py
np_payments/clients/__init__.py
np_payments/clients/esewa/__init__.py
np_payments/clients/esewa/base_esewa.py
np_payments/clients/esewa/esewa.py
np_payments/clients/esewa/esewa_aysnc.py
np_payments/clients/esewa/scheams/esewa_schemas.py
np_payments/transport/httpx_async.py
np_payments/transport/httpx_sync.py
np_payments-0.1.2.dist-info/LICENSE
np_payments-0.1.2.dist-info/METADATA
np_payments-0.1.2.dist-info/WHEEL
np_payments-0.1.2.dist-info/RECORD
