Metadata-Version: 2.3
Name: np-payments
Version: 0.1.2
Summary: Python package for integrating with Nepalese payment gateways like esewa.
License: MIT
Keywords: esewa,khalti,nepal,payment,sdk
Author: Shalin Devkota
Author-email: shalin.devkota01@gmail.com
Requires-Python: >=3.12
Classifier: License :: OSI Approved :: MIT License
Classifier: Operating System :: OS Independent
Classifier: Programming Language :: Python :: 3
Classifier: Programming Language :: Python :: 3.12
Classifier: Programming Language :: Python :: 3.13
Requires-Dist: httpx (>=0.28.1,<0.29.0)
Requires-Dist: pydantic (>=2.11.7,<3.0.0)
Project-URL: Homepage, https://github.com/shalin-devkota/np-payments
Project-URL: Repository, https://github.com/shalin-devkota/np-payments
